pwy/__init__.py
pwy/__main__.py
pwy/__version__.py
pwy/ascii.py
pwy/cli.py
pwy/translation.py
pwy-2.1.2.dist-info/LICENSE
pwy-2.1.2.dist-info/METADATA
pwy-2.1.2.dist-info/WHEEL
pwy-2.1.2.dist-info/entry_points.txt
pwy-2.1.2.dist-info/top_level.txt
pwy-2.1.2.dist-info/RECORD
