Metadata-Version: 2.1
Name: pwy
Version: 2.1.2
Summary: A simple weather information tool
Home-page: https://github.com/cliegargo/pwy
Author: Clint
License: MIT
Platform: UNKNOWN
Classifier: License :: OSI Approved :: MIT License
Classifier: Operating System :: POSIX :: Linux
Classifier: Operating System :: MacOS
Classifier: Operating System :: Microsoft :: Windows
Classifier: Programming Language :: Python :: 3.10
License-File: LICENSE
Requires-Dist: requests
Requires-Dist: rich
